MANIFEST.in
setup.cfg
setup.py
gmaps_url_parser/__init__.py
gmaps_url_parser/core.py
gmaps_url_parser.egg-info/PKG-INFO
gmaps_url_parser.egg-info/SOURCES.txt
gmaps_url_parser.egg-info/dependency_links.txt
gmaps_url_parser.egg-info/not-zip-safe
gmaps_url_parser.egg-info/top_level.txt
tests/__init__.py
tests/test_parser.py