Metadata-Version: 1.1
Name: gmaps-url-parser
Version: 0.1.0
Summary: parse google maps url
Home-page: https://github.com/walidsa3d/gmaps-url-parser
Author: Walid Saad
Author-email: walid.sa3d@gmail.com
License: MIT
Platform: UNKNOWN
Classifier: Development Status :: 4 - Beta
Classifier: Intended Audience :: Developers
Classifier: License :: OSI Approved :: MIT License
Classifier: Programming Language :: Python
Classifier: Topic :: Software Development :: Libraries :: Python Modules
